qrImageIndexerGUI/__init__.py
qrImageIndexerGUI/__main__.py
qrImageIndexerGUI/generate_qr_window.py
qrImageIndexerGUI/image_grid.py
qrImageIndexerGUI/launch_window.py
qrImageIndexerGUI/sort_images_window.py
qrimageindexergui-0.3.4.dist-info/licenses/LICENSE
qrimageindexergui-0.3.4.dist-info/METADATA
qrimageindexergui-0.3.4.dist-info/WHEEL
qrimageindexergui-0.3.4.dist-info/top_level.txt
qrimageindexergui-0.3.4.dist-info/RECORD
