Metadata-Version: 2.4
Name: qrImageIndexerGUI
Version: 0.3.4
Summary: GUI interface for tool for indexing images with QR codes
Author-email: Jonathan Pecar <jonathan.pecar@gmail.com>
License: MIT License
Project-URL: Homepage, https://github.com/jonpecar/qrCodeImageSorterGUI
Keywords: sorter,qrcode,photosorter
Classifier: License :: OSI Approved :: MIT License
Classifier: Programming Language :: Python
Classifier: Programming Language :: Python :: 3
Requires-Python: >=3.7
License-File: LICENSE
Requires-Dist: qrImageIndexer>=0.7.5
Requires-Dist: PyMuPDF
Requires-Dist: pillow
Requires-Dist: natsort
Requires-Dist: customtkinter>=5.0.3
Provides-Extra: dev
Requires-Dist: pytest; extra == "dev"
Requires-Dist: bumpver; extra == "dev"
Requires-Dist: setuptools; extra == "dev"
Requires-Dist: pytest-mock; extra == "dev"
Dynamic: license-file
